Metadata-Version: 2.4
Name: suppgram
Version: 0.0.13
Summary: Minimalistic support system with Telegram-based UI
Author-email: Tigran Saluev <tigran@saluev.com>
Maintainer-email: Tigran Saluev <tigran@saluev.com>
License: MIT License
Project-URL: Homepage, https://github.com/Saluev/suppgram
Project-URL: Documentation, https://suppgram.readthedocs.org
Project-URL: Repository, https://github.com/Saluev/suppgram.git
Project-URL: Issues, https://github.com/Saluev/suppgram/issues
Classifier: Programming Language :: Python :: 3
Classifier: License :: OSI Approved :: MIT License
Classifier: Operating System :: OS Independent
Classifier: Programming Language :: Python :: 3.9
Classifier: Programming Language :: Python :: 3.10
Classifier: Programming Language :: Python :: 3.11
Classifier: Programming Language :: Python :: 3.12
Classifier: Programming Language :: Python :: 3.13
Requires-Python: >=3.8
License-File: LICENSE
Requires-Dist: click~=8.1.7
Provides-Extra: dev
Requires-Dist: mkdocs~=1.5.3; extra == "dev"
Requires-Dist: mkdocstrings~=0.24.0; extra == "dev"
Requires-Dist: mkdocstrings-python~=1.7.5; extra == "dev"
Requires-Dist: mypy~=1.7.1; extra == "dev"
Requires-Dist: mypy-extensions~=1.0.0; extra == "dev"
Requires-Dist: pytest~=7.4.2; extra == "dev"
Requires-Dist: pytest-mock~=3.12.0; extra == "dev"
Requires-Dist: pytest-asyncio~=0.21.1; extra == "dev"
Requires-Dist: ruff~=0.1.6; extra == "dev"
Provides-Extra: mongodb
Requires-Dist: motor~=3.3.2; extra == "mongodb"
Provides-Extra: pubnub
Requires-Dist: aioconsole~=0.6.2; extra == "pubnub"
Requires-Dist: pubnub~=7.3.1; extra == "pubnub"
Provides-Extra: shell
Requires-Dist: aioconsole~=0.6.2; extra == "shell"
Provides-Extra: sqlalchemy
Requires-Dist: aiosqlite~=0.19.0; extra == "sqlalchemy"
Requires-Dist: alembic~=1.13.1; extra == "sqlalchemy"
Requires-Dist: asyncpg~=0.29.0; extra == "sqlalchemy"
Requires-Dist: SQLAlchemy~=2.0.22; extra == "sqlalchemy"
Provides-Extra: sqlalchemy-slim
Requires-Dist: SQLAlchemy~=2.0.22; extra == "sqlalchemy-slim"
Provides-Extra: telegram
Requires-Dist: python-telegram-bot~=20.6; extra == "telegram"
Dynamic: license-file
